setup.py
ricker/__init__.py
ricker/ricker.py
ricker.egg-info/PKG-INFO
ricker.egg-info/SOURCES.txt
ricker.egg-info/dependency_links.txt
ricker.egg-info/top_level.txt
tests/__init__.py
tests/test_ricker.py